{
  "sections": {
    "icon-with-text-1-8-0": {
      "type": "smi-icon-with-text-1-8",
      "blocks": {
        "smi-block-item-0": {
          "type": "icon_with_text",
          "settings": {
            "icon": "box",
            "icon_size": 28,
            "icon_bg": "",
            "heading": "Free shipping",
            "heading_size": "smi-h4",
            "content": "",
            "button_label": "",
            "link1": ""
          }
        },
        "smi-block-item-1": {
          "type": "icon_with_text",
          "settings": {
            "icon": "return",
            "icon_size": 28,
            "icon_bg": "",
            "heading": "30 Days Free returns",
            "heading_size": "smi-h4",
            "content": "",
            "button_label": "",
            "link1": ""
          }
        },
        "smi-block-item-2": {
          "type": "icon_with_text",
          "settings": {
            "icon": "verify",
            "icon_size": 28,
            "icon_bg": "",
            "heading": "Quality guarantee",
            "heading_size": "smi-h4",
            "content": "",
            "button_label": "",
            "link1": ""
          }
        }
      },
      "block_order": [
        "smi-block-item-0",
        "smi-block-item-1",
        "smi-block-item-2"
      ],
      "disabled": true,
      "settings": {
        "container_full_width": true,
        "sub_heading": "",
        "heading": "",
        "heading_size": "smi-h2",
        "description": "",
        "heading_alignment": "center",
        "content_alignment": "left",
        "number_of_columns_on_desktop": "3",
        "number_of_columns_on_mobile": "1",
        "enable_swipe_on_mobile": false,
        "icon_position": "left",
        "color_scheme": "scheme_1",
        "padding_top": 16,
        "padding_bottom": 16
      }
    },
    "image-hero-1-2-1": {
      "type": "smi-image-hero-1-2",
      "settings": {
        "container_full_width": false,
        "image": "shopify:\/\/shop_images\/dog-leashes-202408.webp",
        "hero_height": "medium",
        "subheading": "",
        "heading": "Discover latest trends",
        "heading_size": "smi-h1",
        "description": "From cozy winter wear to breezy summer outfits",
        "first_button_label": "SHOP NOW",
        "first_button_link": "",
        "first_button_style": "solid",
        "second_button_label": "",
        "second_button_link": "",
        "second_button_style": "outline",
        "desktop_content_position": "end_center",
        "desktop_content_alignment": "center",
        "mobile_content_alignment": "center",
        "content_max_width": 540,
        "content_background_opacity": 0,
        "color_scheme": "scheme_4",
        "image_overlay": "linear-gradient(180deg, rgba(53, 27, 1, 0.1882), rgba(53, 27, 1, 0.1882) 100%)"
      }
    },
    "featured-collection-4-2-17": {
      "type": "smi-featured-collection-4-2",
      "blocks": {
        "smi-block-item-0": {
          "type": "colection_tab",
          "settings": {
            "collection": "seasonal-specials-mamzoo-sale",
            "number_items": 10,
            "label_collection": ""
          }
        }
      },
      "block_order": [
        "smi-block-item-0"
      ],
      "settings": {
        "full_width": false,
        "enable_spacing": true,
        "sub_heading": "",
        "heading": "SEASONAL SPECIALS",
        "heading_size": "smi-h2",
        "description": "",
        "heading_alignment": "center",
        "media_ratio": "auto",
        "media_shape": "default",
        "content_alignment": "center",
        "show_second_image": true,
        "show_vendor": false,
        "show_swatch_color": true,
        "number_of_columns_on_desktop": "5",
        "number_of_columns_on_mobile": "1",
        "enable_swipe_on_mobile": true,
        "tab_style": "circle-style-2",
        "button_style": "solid",
        "color_scheme": "scheme_1",
        "product_color_scheme": "scheme_2",
        "padding_top": 50,
        "padding_bottom": 50
      }
    },
    "collection-list-1-7-2": {
      "type": "smi-collection-list-1-7",
      "blocks": {
        "smi-block-item-0": {
          "type": "collection",
          "settings": {
            "collection": "midi-dresses-1",
            "subheading": "",
            "heading": "Midi dresses",
            "heading_size": "smi-h4",
            "description": "17 Items",
            "link": "",
            "button_label": "",
            "button_style": "text"
          }
        },
        "smi-block-item-1": {
          "type": "collection",
          "settings": {
            "collection": "bag-1",
            "subheading": "",
            "heading": "Bag",
            "heading_size": "smi-h4",
            "description": "15 Items",
            "link": "",
            "button_label": "",
            "button_style": "text"
          }
        },
        "smi-block-item-2": {
          "type": "collection",
          "settings": {
            "collection": "ballet",
            "subheading": "",
            "heading": "",
            "heading_size": "smi-h4",
            "description": "6 Items",
            "link": "",
            "button_label": "",
            "button_style": "solid"
          }
        },
        "smi-block-item-3": {
          "type": "collection",
          "settings": {
            "collection": "cardigan",
            "subheading": "",
            "heading": "Cardigan",
            "heading_size": "smi-h4",
            "description": "20 Items",
            "link": "",
            "button_label": "",
            "button_style": "text"
          }
        },
        "smi-block-item-4": {
          "type": "collection",
          "settings": {
            "collection": "dress-shirts",
            "subheading": "",
            "heading": "Dress shrits",
            "heading_size": "smi-h4",
            "description": "10 Items",
            "link": "",
            "button_label": "",
            "button_style": "text"
          }
        },
        "smi-block-item-5": {
          "type": "collection",
          "settings": {
            "collection": "jacket-1",
            "subheading": "",
            "heading": "Jackets",
            "heading_size": "smi-h4",
            "description": "18 Items",
            "link": "",
            "button_label": "",
            "button_style": "text"
          }
        }
      },
      "block_order": [
        "smi-block-item-0",
        "smi-block-item-1",
        "smi-block-item-2",
        "smi-block-item-3",
        "smi-block-item-4",
        "smi-block-item-5"
      ],
      "disabled": true,
      "settings": {
        "container_full_width": true,
        "sub_heading": "",
        "heading": "Shop by categories",
        "heading_size": "smi-h2",
        "description": "",
        "heading_alignment": "center",
        "content_alignment": "center",
        "media_ratio": "1\/1",
        "media_shape": "round",
        "arrow_style": "arr-style-1",
        "sticky_page_dot_style": "line-style-4",
        "auto_rotate_slides": false,
        "change_slides_every": 5,
        "number_of_columns_on_desktop": "5",
        "number_of_columns_on_mobile": "2",
        "slider_overflow": true,
        "color_scheme": "scheme_1",
        "padding_top": 50,
        "padding_bottom": 50
      }
    },
    "comparison-table-1-2-3": {
      "type": "smi-comparison-table-1-2",
      "blocks": {
        "smi-block-item-0": {
          "type": "heading-comparison-table",
          "settings": {
            "image_width_1": 200,
            "heading_1": "Smind",
            "heading_size_1": "smi-h5",
            "image_width_2": 200,
            "heading_2": "Others",
            "heading_size_2": "smi-h5"
          }
        },
        "smi-block-item-1": {
          "type": "row-comparison-table",
          "settings": {
            "heading_row": "High quality",
            "heading_size_row": "smi-h5",
            "content_row": "<p>The breathable fabric moves with the body, providing theflexibility needed for various activities.<\/p>",
            "icon_1": "check_3",
            "content_1": "",
            "icon_2": "time_3",
            "content_2": ""
          }
        },
        "smi-block-item-2": {
          "type": "row-comparison-table",
          "settings": {
            "heading_row": "Customer support",
            "heading_size_row": "smi-h5",
            "content_row": "<p>Indulge in the perfect blend of sophistication and comfortin designs tailored for those who appreciate timeless.<\/p>",
            "icon_1": "check_3",
            "content_1": "",
            "icon_2": "time_3",
            "content_2": ""
          }
        },
        "smi-block-item-3": {
          "type": "row-comparison-table",
          "settings": {
            "heading_row": "Diverse styles",
            "heading_size_row": "smi-h5",
            "content_row": "<p>Stepping into the realm of bohemian fashion is akin to entering a world of whimsy and carefree charm.<\/p>",
            "icon_1": "check_3",
            "content_1": "",
            "icon_2": "time_3",
            "content_2": ""
          }
        },
        "smi-block-item-4": {
          "type": "row-comparison-table",
          "settings": {
            "heading_row": "Easy to use",
            "heading_size_row": "smi-h5",
            "content_row": "<p>A flowing floral maxi dress embodies the spirit of boho chic, with its free-spirited silhouette and vibrant patterns.<\/p>",
            "icon_1": "check_3",
            "content_1": "",
            "icon_2": "time_3",
            "content_2": ""
          }
        }
      },
      "block_order": [
        "smi-block-item-0",
        "smi-block-item-1",
        "smi-block-item-2",
        "smi-block-item-3",
        "smi-block-item-4"
      ],
      "disabled": true,
      "settings": {
        "use_content_container_style_settings": true,
        "sub_heading": "HOW WE COMPARE",
        "heading": "Elevate your look with details",
        "heading_size": "smi-h2",
        "description": "",
        "heading_alignment": "center",
        "content_max_width": 1200,
        "show_column_separation": false,
        "highlighted_column": "1",
        "icon_size": 28,
        "color_scheme": "scheme_1",
        "color_include_icon": "#3ed660",
        "color_exclude_icon": "#eb001b",
        "padding_top": 50,
        "padding_bottom": 50
      }
    },
    "testimonial-1-7-4": {
      "type": "smi-testimonial-1-7",
      "blocks": {
        "smi-block-item-0": {
          "type": "testimonial_block",
          "settings": {
            "heading": "Wow! Impressed",
            "heading_size": "smi-h5",
            "description": "I absolutely love the fashion choices on this website. The quality and variety of clothing are top-notch. It's become my go-to place for trendy outfits.",
            "author_name": "Jame Bones",
            "author_info": "Customers in U.S.A",
            "author_image": "shopify:\/\/shop_images\/smi-customer-7.jpg",
            "author_shape": "round",
            "star": "5"
          }
        },
        "smi-block-item-1": {
          "type": "testimonial_block",
          "settings": {
            "heading": "I love this product.",
            "heading_size": "smi-h5",
            "description": "Great website for stylish clothing. I've found some fantastic pieces here. The only thing I'd suggest is more size options for a wider range of customers.",
            "author_name": "Emily Blunt",
            "author_info": "Customers in U.S.A",
            "author_image": "shopify:\/\/shop_images\/smi-customer-3.jpg",
            "author_shape": "round",
            "star": "4"
          }
        },
        "smi-block-item-2": {
          "type": "testimonial_block",
          "settings": {
            "heading": "Highly recommended!",
            "heading_size": "smi-h5",
            "description": "This website has transformed my wardrobe! I can always count on them for the latest fashion trends. The service is excellent, and the delivery is fast.",
            "author_name": "Olivia Wilde",
            "author_info": "Customers in U.S.A",
            "author_image": "shopify:\/\/shop_images\/smi-customer-5.jpg",
            "author_shape": "round",
            "star": "4.5"
          }
        },
        "smi-block-item-3": {
          "type": "testimonial_block",
          "settings": {
            "heading": "Fast delivery.",
            "heading_size": "smi-h5",
            "description": "Absolutely in love with my recent fashion haul! The quality of the clothes exceeded my expectations. Will definitely be a repeat customer!",
            "author_name": "Olivia Blunt",
            "author_info": "Customers in U.S.A",
            "author_image": "shopify:\/\/shop_images\/smi-customer-2.jpg",
            "author_shape": "round",
            "star": "5"
          }
        },
        "smi-block-item-4": {
          "type": "testimonial_block",
          "settings": {
            "heading": "Dress fits perfectly.",
            "heading_size": "smi-h5",
            "description": "I love it so much! The outfits fit perfectly, and the fabrics are so comfortable. Can't wait to show off my new looks. Highly recommend this brand.",
            "author_name": "Emily Wilde",
            "author_info": "Customers in U.S.A",
            "author_image": "shopify:\/\/shop_images\/smi-customer-5.jpg",
            "author_shape": "round",
            "star": "5"
          }
        },
        "smi-block-item-5": {
          "type": "testimonial_block",
          "settings": {
            "heading": "Fantastic choices!",
            "heading_size": "smi-h5",
            "description": "Impressed with the fashion quality and unique designs. The pieces I ordered arrived promptly. A great online shopping experience overall!",
            "author_name": "Isabella Gonzalez",
            "author_info": "Customers in U.S.A",
            "author_image": "shopify:\/\/shop_images\/smi-customer-4.jpg",
            "author_shape": "round",
            "star": "5"
          }
        },
        "smi-block-item-6": {
          "type": "testimonial_block",
          "settings": {
            "heading": "Impressed with it!",
            "heading_size": "smi-h5",
            "description": "Fantastic fashion choices! The clothing is not only stylish but also comfortable. Quick shipping adds to the positive experience. Will shop here again!",
            "author_name": "Alexei Petrovich",
            "author_info": "Customers in U.S.A",
            "author_image": "shopify:\/\/shop_images\/smi-customer-8.jpg",
            "author_shape": "round",
            "star": "4"
          }
        }
      },
      "block_order": [
        "smi-block-item-0",
        "smi-block-item-1",
        "smi-block-item-2",
        "smi-block-item-3",
        "smi-block-item-4",
        "smi-block-item-5",
        "smi-block-item-6"
      ],
      "disabled": true,
      "settings": {
        "full_width": true,
        "sub_heading": "TESTIMONIALS",
        "heading": "Our happy customers share",
        "heading_size": "smi-h2",
        "description": "",
        "heading_alignment": "center",
        "content_alignment": "center",
        "arrow_style": "none",
        "sticky_page_dot_style": "line-style-1",
        "auto_rotate_slides": false,
        "change_slide_every": 5,
        "number_of_item": "4",
        "color_scheme": "scheme_1",
        "color_rating": "#f8a427",
        "padding_top": 50,
        "padding_bottom": 50
      }
    },
    "blog-posts-1-7-5": {
      "type": "smi-blog-posts-1-7",
      "settings": {
        "container_full_width": false,
        "enable_spacing_between_items": true,
        "sub_heading": "",
        "heading": "Latest blog posts",
        "heading_size": "smi-h2",
        "description": "",
        "heading_alignment": "center",
        "blog": "mamzoo-pet-supplies-expert-care-blog",
        "maximum_item_to_show": 10,
        "media_ratio": "1\/1",
        "media_shape": "default",
        "content_alignment": "center",
        "show_tags": false,
        "show_date": false,
        "show_author": false,
        "show_comment_count": false,
        "show_excerpt": false,
        "button_style": "none",
        "arrow_style": "arr-style-1",
        "sticky_page_dot_style": "none",
        "view_all_button_style": "outline",
        "auto_rotate_slides": true,
        "change_slides_every": 5,
        "number_of_columns_on_desktop": "4",
        "slider_overflow": false,
        "color_scheme": "scheme_1",
        "blog_color_scheme": "scheme_1",
        "padding_top": 50,
        "padding_bottom": 50
      }
    },
    "cart-drawer-1-1-6": {
      "type": "smi-cart-drawer-1-1",
      "blocks": {
        "smi-block-item-0": {
          "type": "cart_note",
          "settings": {
            "label_text": "<p>Special instructions for seller<\/p>"
          }
        }
      },
      "block_order": [
        "smi-block-item-0"
      ],
      "settings": {
        "show_taxes_policy": true,
        "show_view_cart": true,
        "collection": "cardigan",
        "color_scheme": "scheme_2"
      }
    },
    "collapsible-content-1-1-7": {
      "type": "smi-collapsible-content-1-1",
      "blocks": {
        "smi-block-item-0": {
          "type": "collapsible_category",
          "settings": {
            "icon": "question",
            "icon_size": 24,
            "heading": "Orders & Shipping",
            "heading_size": "smi-h4"
          }
        },
        "smi-block-item-1": {
          "type": "collapsible_content",
          "settings": {
            "icon": "none",
            "icon_size": 24,
            "heading": "How do I care for my clothing?",
            "heading_size": "smi-h5",
            "content": "<p>Crop hoodie sweatshirt. Sewn neck with hood with drawstring for adjustment, short sleeves. There is a kangaroo pocket on the front. Discoloration effect fabric, decorated with torn details. It is very easy to coordinate street style clothes.<\/p>",
            "collapse_content_page": ""
          }
        },
        "smi-block-item-2": {
          "type": "collapsible_content",
          "settings": {
            "icon": "none",
            "icon_size": 24,
            "heading": "Do you offer international shipping?",
            "heading_size": "smi-h5",
            "content": "<p>Crop hoodie sweatshirt. Sewn neck with hood with drawstring for adjustment, short sleeves. There is a kangaroo pocket on the front. Discoloration effect fabric, decorated with torn details. It is very easy to coordinate street style clothes, bringing a dynamic and youthful feeling.<\/p>",
            "collapse_content_page": ""
          }
        },
        "smi-block-item-3": {
          "type": "collapsible_content",
          "settings": {
            "icon": "none",
            "icon_size": 24,
            "heading": "Can I return or exchange items?",
            "heading_size": "smi-h5",
            "content": "<p>Crop hoodie sweatshirt. Sewn neck with hood with drawstring for adjustment, short sleeves. There is a kangaroo pocket on the front. Discoloration effect fabric, decorated with torn details. It is very easy to coordinate street style clothes, bringing a dynamic and youthful feeling.<\/p>",
            "collapse_content_page": ""
          }
        },
        "smi-block-item-4": {
          "type": "collapsible_content",
          "settings": {
            "icon": "none",
            "icon_size": 24,
            "heading": "How often do you release new collections?",
            "heading_size": "smi-h5",
            "content": "<p>Crop hoodie sweatshirt. Sewn neck with hood with drawstring for adjustment, short sleeves. There is a kangaroo pocket on the front. Discoloration effect fabric, decorated with torn details. It is very easy to coordinate street style clothes, bringing a dynamic and youthful feeling.<\/p>",
            "collapse_content_page": ""
          }
        },
        "smi-block-item-5": {
          "type": "collapsible_category",
          "settings": {
            "icon": "question",
            "icon_size": 24,
            "heading": "Returns & Refunds",
            "heading_size": "smi-h4"
          }
        },
        "smi-block-item-6": {
          "type": "collapsible_content",
          "settings": {
            "icon": "none",
            "icon_size": 24,
            "heading": "What is your return policy?",
            "heading_size": "smi-h5",
            "content": "<p>To initiate a return or exchange, please log into your account, go to the 'Order History' section, and select the order you wish to return. Follow the provided instructions to complete the process.<\/p>",
            "collapse_content_page": ""
          }
        },
        "smi-block-item-7": {
          "type": "collapsible_content",
          "settings": {
            "icon": "none",
            "icon_size": 24,
            "heading": "How long does it take to process a refund?",
            "heading_size": "smi-h5",
            "content": "<p>Crop hoodie sweatshirt. Sewn neck with hood with drawstring for adjustment, short sleeves. There is a kangaroo pocket on the front. Discoloration effect fabric, decorated with torn details. It is very easy to coordinate street style clothes.<\/p>",
            "collapse_content_page": ""
          }
        },
        "smi-block-item-8": {
          "type": "collapsible_content",
          "settings": {
            "icon": "none",
            "icon_size": 24,
            "heading": "Do I have to pay for return shipping?",
            "heading_size": "smi-h5",
            "content": "<p>Crop hoodie sweatshirt. Sewn neck with hood with drawstring for adjustment, short sleeves. There is a kangaroo pocket on the front. Discoloration effect fabric, decorated with torn details. It is very easy to coordinate street style clothes, bringing a dynamic and youthful feeling.<\/p>",
            "collapse_content_page": ""
          }
        },
        "smi-block-item-9": {
          "type": "collapsible_content",
          "settings": {
            "icon": "none",
            "icon_size": 24,
            "heading": "How often do you release new collections?",
            "heading_size": "smi-h5",
            "content": "<p>Crop hoodie sweatshirt. Sewn neck with hood with drawstring for adjustment, short sleeves. There is a kangaroo pocket on the front. Discoloration effect fabric, decorated with torn details. It is very easy to coordinate street style clothes, bringing a dynamic and youthful feeling.<\/p>",
            "collapse_content_page": ""
          }
        },
        "smi-block-item-10": {
          "type": "button",
          "settings": {
            "first_button_label": "View all faq",
            "first_button_link": "",
            "first_button_style": "solid_arrow",
            "second_button_label": "",
            "second_button_link": "",
            "second_button_style": "solid",
            "button_full_width": false
          }
        }
      },
      "block_order": [
        "smi-block-item-0",
        "smi-block-item-1",
        "smi-block-item-2",
        "smi-block-item-3",
        "smi-block-item-4",
        "smi-block-item-5",
        "smi-block-item-6",
        "smi-block-item-7",
        "smi-block-item-8",
        "smi-block-item-9",
        "smi-block-item-10"
      ],
      "disabled": true,
      "settings": {
        "sub_heading": "",
        "heading": "Common questions",
        "heading_size": "smi-h2",
        "description": "<p>Have questions about our products, or services? Find answers to the most common inquiries here<\/p>",
        "heading_alignment": "center",
        "collapsible_type": "3",
        "content_position": "center",
        "content_alignment": "left",
        "content_max_width": 770,
        "open_first_collapsible_row": true,
        "color_scheme": "scheme_2",
        "padding_top": 50,
        "padding_bottom": 50
      }
    },
    "image-with-text-4-7-8": {
      "type": "smi-image-with-text-4-7",
      "blocks": {
        "smi-block-item-0": {
          "type": "heading",
          "settings": {
            "sub_heading": "HOT DEALS UP TO 30%",
            "heading": "Get 30% off on all new arrivals products",
            "heading_size": "smi-h2",
            "description": "<p>Express yourself with our trendy and versatile collection of fashion essentials, carefully curated to elevate.<\/p>"
          }
        },
        "smi-block-item-1": {
          "type": "button",
          "settings": {
            "first_button_label": "Learn more",
            "first_button_link": "",
            "first_button_style": "outline",
            "second_button_label": "Shop now",
            "second_button_link": "",
            "second_button_style": "solid",
            "button_full_width": false
          }
        }
      },
      "block_order": [
        "smi-block-item-0",
        "smi-block-item-1"
      ],
      "disabled": true,
      "settings": {
        "full_width": "container-fluid-no-padding",
        "upload_image": "shopify:\/\/shop_images\/smi-smi-smi-clothing_-_30_d7ddc095-4eff-4fb1-b403-704587c5231a.jpg",
        "desktop_media_width": "50",
        "desktop_media_position": "row-reverse",
        "media_height": "medium",
        "content_position": "center",
        "content_alignment": "center",
        "content_max_width": 470,
        "color_scheme": "scheme_5",
        "padding_top": 0,
        "padding_bottom": 0
      }
    },
    "logo-list-4-1-9": {
      "type": "smi-logo-list-4-1",
      "blocks": {
        "smi-block-item-0": {
          "type": "logo",
          "settings": {
            "logo_width": 160,
            "link": ""
          }
        },
        "smi-block-item-1": {
          "type": "logo",
          "settings": {
            "logo_width": 160,
            "link": ""
          }
        },
        "smi-block-item-2": {
          "type": "logo",
          "settings": {
            "logo_width": 160,
            "link": ""
          }
        },
        "smi-block-item-3": {
          "type": "logo",
          "settings": {
            "logo_width": 160,
            "link": ""
          }
        },
        "smi-block-item-4": {
          "type": "logo",
          "settings": {
            "logo_width": 160,
            "link": ""
          }
        },
        "smi-block-item-5": {
          "type": "logo",
          "settings": {
            "logo_width": 160,
            "link": ""
          }
        },
        "smi-block-item-6": {
          "type": "logo",
          "settings": {
            "logo_width": 160,
            "link": ""
          }
        }
      },
      "block_order": [
        "smi-block-item-0",
        "smi-block-item-1",
        "smi-block-item-2",
        "smi-block-item-3",
        "smi-block-item-4",
        "smi-block-item-5",
        "smi-block-item-6"
      ],
      "disabled": true,
      "settings": {
        "container_full_width": false,
        "use_media_style_from_theme_settings": false,
        "sub_heading": "AS FEATURED IN",
        "heading": "",
        "heading_size": "smi-h2",
        "description": "",
        "heading_alignment": "center",
        "arrow_style": "none",
        "sticky_page_dot_style": "dot-style-1",
        "auto_rotate_slides": true,
        "change_slides_every": 5,
        "number_of_columns_on_desktop": "5",
        "number_of_columns_on_mobile": "1",
        "color_scheme": "scheme_1",
        "padding_top": 50,
        "padding_bottom": 50
      }
    },
    "rich-content-1-5-10": {
      "type": "smi-rich-content-1-5",
      "blocks": {
        "smi-block-item-0": {
          "type": "heading",
          "settings": {
            "sub_heading": "",
            "heading": "Your perfect fashion companion",
            "heading_size": "smi-h2",
            "description": "<p>From chic carryalls to versatile backpacks, each piece is a fusion of trendsetting design and practical features.  Embrace the perfect blend of form and function.<\/p>"
          }
        },
        "smi-block-item-1": {
          "type": "icon_with_text",
          "settings": {
            "icon": "bag-handle",
            "icon_size": 24,
            "icon_bg": "rgba(0,0,0,0)",
            "heading": "",
            "heading_size": "smi-h4",
            "content": "<p>Fashion and Style<\/p>",
            "icon_position": "left",
            "half_width_on_large_screen": false
          }
        },
        "smi-block-item-2": {
          "type": "icon_with_text",
          "settings": {
            "icon": "tag",
            "icon_size": 24,
            "icon_bg": "",
            "heading": "",
            "heading_size": "smi-h5",
            "content": "<p>Storage and Organization<\/p>",
            "icon_position": "left",
            "half_width_on_large_screen": false
          }
        },
        "smi-block-item-3": {
          "type": "icon_with_text",
          "settings": {
            "icon": "love",
            "icon_size": 24,
            "icon_bg": "",
            "heading": "",
            "heading_size": "smi-h5",
            "content": "<p>Convenience and Mobility<\/p>",
            "icon_position": "left",
            "half_width_on_large_screen": false
          }
        },
        "smi-block-item-4": {
          "type": "button",
          "settings": {
            "first_button_label": "Learn more",
            "first_button_link": "",
            "first_button_style": "solid",
            "second_button_label": "Shop now",
            "second_button_link": "",
            "second_button_style": "outline",
            "button_full_width": false
          }
        }
      },
      "block_order": [
        "smi-block-item-0",
        "smi-block-item-1",
        "smi-block-item-2",
        "smi-block-item-3",
        "smi-block-item-4"
      ],
      "disabled": true,
      "settings": {
        "full_width": "container",
        "upload_image": "shopify:\/\/shop_images\/smi-image_clothing-02_3.jpg",
        "desktop_media_width": "50",
        "desktop_media_position": "row",
        "media_ratio": "3\/4",
        "media_shape": "default",
        "content_position": "left",
        "content_alignment": "left",
        "content_max_width": 520,
        "color_scheme": "scheme_1",
        "padding_top": 50,
        "padding_bottom": 50
      }
    },
    "slideshow-2-3-11": {
      "type": "smi-slideshow-2-3",
      "blocks": {
        "smi-block-item-0": {
          "type": "image_slide",
          "settings": {
            "image": "shopify:\/\/shop_images\/smi-smi-clothing-classic-21.jpg",
            "subheading": "ELEVATE YOUR LOOK",
            "heading": "Make a statement with your style",
            "heading_size": "smi-h1",
            "description": "Each element of the suit is carefully designed to empower the wearer, whether navigating the boardroom.",
            "first_button_label": "Explore all",
            "first_button_link": "",
            "first_button_style": "solid",
            "second_button_label": "",
            "second_button_link": "",
            "second_button_style": "outline"
          }
        },
        "smi-block-item-1": {
          "type": "image_slide",
          "settings": {
            "image": "shopify:\/\/shop_images\/smi-smi-clothing-classic-20.jpg",
            "subheading": "EFFORTLESS ELEGANCE",
            "heading": "Instant fashion transformations",
            "heading_size": "smi-h1",
            "description": "From cozy winter wear to breezy summer outfits, explore versatile fashion choices that adapt to the changing seasons.",
            "first_button_label": "Shop now",
            "first_button_link": "",
            "first_button_style": "solid",
            "second_button_label": "",
            "second_button_link": "",
            "second_button_style": "outline"
          }
        },
        "smi-block-item-2": {
          "type": "image_slide",
          "settings": {
            "image": "shopify:\/\/shop_images\/smi-smi-clothing_-_30.jpg",
            "subheading": "YEAR-ROUND STYLE",
            "heading": "Fashion for active lifestyles",
            "heading_size": "smi-h1",
            "description": "Indulge in the perfect blend of sophistication and comfort in designs tailored for those who appreciate timeless style.",
            "first_button_label": "Shop product",
            "first_button_link": "",
            "first_button_style": "solid",
            "second_button_label": "",
            "second_button_link": "",
            "second_button_style": "outline"
          }
        }
      },
      "block_order": [
        "smi-block-item-0",
        "smi-block-item-1",
        "smi-block-item-2"
      ],
      "disabled": true,
      "settings": {
        "container_full_width": true,
        "desktop_media_width": "50",
        "desktop_media_position": "left",
        "slide_height": "large",
        "sticky_page_dot_style": "dot-style-3",
        "auto_rotate_slides": true,
        "change_slides_every": 3,
        "slide_transition": "slide",
        "content_position": "center",
        "content_alignment": "center",
        "content_max_width": 700,
        "color_scheme": "scheme_5",
        "padding_top": 0,
        "padding_bottom": 0
      }
    },
    "shop-the-look-1-2-12": {
      "type": "smi-shop-the-look-1-2",
      "blocks": {
        "smi-block-item-0": {
          "type": "look",
          "settings": {
            "image": "shopify:\/\/shop_images\/smi-review_clothing-55.jpg",
            "product_1": "cozy-cloud-puffer-jacket",
            "horizontal_position_1": 65,
            "vertical_position_1": 35,
            "product_2": "aubre-open-back-essential-maxi",
            "horizontal_position_2": 54,
            "vertical_position_2": 65,
            "product_3": "",
            "horizontal_position_3": 50,
            "vertical_position_3": 50,
            "product_4": "",
            "horizontal_position_4": 70,
            "vertical_position_4": 70,
            "product_5": "",
            "horizontal_position_5": 80,
            "vertical_position_5": 40
          }
        },
        "smi-block-item-1": {
          "type": "look",
          "settings": {
            "image": "shopify:\/\/shop_images\/smi-review_clothing-22.jpg",
            "product_1": "we-the-free-night-moves-shirt",
            "horizontal_position_1": 57,
            "vertical_position_1": 40,
            "product_2": "closed-nikka-mid-rise-wide-leg-jeans",
            "horizontal_position_2": 46,
            "vertical_position_2": 66,
            "product_3": "",
            "horizontal_position_3": 50,
            "vertical_position_3": 65,
            "product_4": "",
            "horizontal_position_4": 70,
            "vertical_position_4": 70,
            "product_5": "",
            "horizontal_position_5": 80,
            "vertical_position_5": 40
          }
        },
        "smi-block-item-2": {
          "type": "look",
          "settings": {
            "image": "shopify:\/\/shop_images\/smi-review_clothing-42.jpg",
            "product_1": "bodhi-fisher-sneakers",
            "horizontal_position_1": 49,
            "vertical_position_1": 56,
            "product_2": "",
            "horizontal_position_2": 30,
            "vertical_position_2": 40,
            "product_3": "",
            "horizontal_position_3": 50,
            "vertical_position_3": 50,
            "product_4": "",
            "horizontal_position_4": 70,
            "vertical_position_4": 70,
            "product_5": "",
            "horizontal_position_5": 80,
            "vertical_position_5": 40
          }
        }
      },
      "block_order": [
        "smi-block-item-0",
        "smi-block-item-1",
        "smi-block-item-2"
      ],
      "disabled": true,
      "settings": {
        "sub_heading": "BE UNIQUE, BE AUTHENTIC",
        "heading": "Unlocking your style potential",
        "heading_size": "smi-h2",
        "description": "",
        "heading_alignment": "center",
        "image_position": "left",
        "image_style": "style_as_product_card",
        "hotspot_style": "2",
        "media_ratio": "3\/4",
        "media_shape": "default",
        "content_alignment": "left",
        "show_second_image": true,
        "show_vendor": true,
        "show_swatch_color": true,
        "arrow_style": "arr-square-style-3",
        "sticky_page_dot_style": "line-style-2",
        "color_scheme": "scheme_2",
        "product_card_color_scheme": "scheme_1",
        "hotspot": "#2e2e2e",
        "padding_top": 50,
        "padding_bottom": 50
      }
    },
    "scrolling-text-1-3-13": {
      "type": "smi-scrolling-text-1-3",
      "blocks": {
        "smi-block-item-0": {
          "type": "text",
          "settings": {
            "heading": "- Sale up to 50%",
            "heading_size": "smi-h4",
            "outline_text": false
          }
        }
      },
      "block_order": [
        "smi-block-item-0"
      ],
      "disabled": true,
      "settings": {
        "container_full_width": true,
        "show_top_divider": true,
        "show_bottom_divider": true,
        "scroll_direction": "ltr",
        "scrolling_speed": 2,
        "gap_between_content": 8,
        "color_scheme": "scheme_1",
        "padding_top": 20,
        "padding_bottom": 20
      }
    },
    "featured-product-1-1-14": {
      "type": "smi-featured-product-1-1",
      "blocks": {
        "smi-block-item-0": {
          "type": "product_title",
          "settings": {
            "heading_size": "smi-h3"
          }
        },
        "smi-block-item-1": {
          "type": "product_price",
          "settings": {
            "show_sale_badge": true,
            "show_shipping_notice": false
          }
        },
        "smi-block-item-2": {
          "type": "product_inventory_status",
          "settings": {
            "low_inventory_threshold": 20,
            "show_inventory_count": true
          }
        },
        "smi-block-item-3": {
          "type": "shop_pay_installments",
          "settings": {
          }
        },
        "smi-block-item-4": {
          "type": "product_description",
          "disabled": true,
          "settings": {
            "collapse_desc": false,
            "show_desc_below": false,
            "icon": "box",
            "icon_size": 24,
            "collapse_heading": "Description",
            "heading_size": "smi-h5"
          }
        },
        "smi-block-item-5": {
          "type": "product_variant",
          "settings": {
            "hide_sold_out_variant": false,
            "selector_type": "button",
            "color_selector_type": "color_swatch"
          }
        },
        "smi-block-item-6": {
          "type": "product_size_chart",
          "settings": {
            "show_icon": true,
            "append_to_variant_block": "Size chart"
          }
        },
        "smi-block-item-7": {
          "type": "product_purchase",
          "settings": {
            "show_dynamic_checkout": true,
            "show_recipient_information": false
          }
        },
        "smi-block-item-8": {
          "type": "product_collapse_content",
          "settings": {
            "show_desc_below": false,
            "icon": "none",
            "icon_size": 24,
            "collapse_heading": "Details",
            "heading_size": "smi-h5",
            "collapse_content": "<p>Style No. 78133949; Color Code: 066<\/p><p>Just as versatile as it is vintage-inspired, this so special sweater dress is featured in a long sleeve, sweater-inspired design with zip-front, collared neckline for added dimension.<\/p><p><strong>Fit:<\/strong> Bodycon fit<br\/><strong>Features:<\/strong> Long sleeve style, zip-front neckline, ribbed and cable knit detailing throughout<br\/><strong>Why We Love It:<\/strong> The definition of an effortless essential, this timeless mini dress is sure to be your go-to pick all season long.<\/p><p><strong>Care\/Import<\/strong><\/p><p>Hand Wash Cold<\/p><p>Import<\/p><p><strong>Measurements for size small<\/strong><\/p><ul><li>Bust: 27.5 in<\/li><li>Length: 31.5 in<\/li><li>Sleeve Length: 25 in<\/li><\/ul>",
            "collapse_content_page": ""
          }
        },
        "smi-block-item-9": {
          "type": "product_collapse_content",
          "settings": {
            "show_desc_below": false,
            "icon": "none",
            "icon_size": 24,
            "collapse_heading": "Content",
            "heading_size": "smi-h5",
            "collapse_content": "<ul><li>49% Cotton<\/li><li>51% Polyester<\/li><\/ul>",
            "collapse_content_page": ""
          }
        },
        "smi-block-item-10": {
          "type": "product_collapse_content",
          "settings": {
            "show_desc_below": false,
            "icon": "none",
            "icon_size": 24,
            "collapse_heading": "Shipping & returns",
            "heading_size": "smi-h5",
            "collapse_content": "<p><strong>Shipping:<\/strong><\/p><ul><li>Standard shipping typically takes 3-5 business days.<\/li><li>Expedited shipping delivers within 1-2 business days after order processing.<\/li><\/ul><p><strong>Returns:<\/strong><\/p><p>Please review our <a href=\"#\" target=\"_blank\" title=\"#\">Return policy <\/a>for merchandise exchanges and refunds.<\/p>",
            "collapse_content_page": ""
          }
        }
      },
      "block_order": [
        "smi-block-item-0",
        "smi-block-item-1",
        "smi-block-item-2",
        "smi-block-item-3",
        "smi-block-item-4",
        "smi-block-item-5",
        "smi-block-item-6",
        "smi-block-item-7",
        "smi-block-item-8",
        "smi-block-item-9",
        "smi-block-item-10"
      ],
      "settings": {
        "container_full_width": false,
        "enable_sticky_content_on_desktop": true,
        "sub_heading": "",
        "heading": "",
        "heading_size": "smi-h2",
        "description": "",
        "heading_alignment": "center",
        "product": "lazymax-5-in-1-portable-dog-water-bottle",
        "desktop_media_width": "50",
        "desktop_media_position": "left",
        "constrain_media_to_screen_height": "fill",
        "desktop_layout": "pagination",
        "image_zoom": "open-lightbox",
        "mobile_layout": "hide_thumbnails",
        "hide_variants": false,
        "video_looping": false,
        "color_scheme": "scheme_1",
        "padding_top": 50,
        "padding_bottom": 50
      }
    },
    "email-signup-2-5-15": {
      "type": "smi-email-signup-2-5",
      "blocks": {
        "smi-block-item-0": {
          "type": "email_form",
          "settings": {
            "style_email_signup": "4",
            "email_notice_text": "No spam, unsubscribe anytime!"
          }
        }
      },
      "block_order": [
        "smi-block-item-0"
      ],
      "disabled": true,
      "settings": {
        "sub_heading": "SUBSCRIBE",
        "heading": "Let's stay in touch",
        "heading_size": "smi-h2",
        "description": "<p>Stay in the loop with the latest product releases, exclusive discounts, and our special offers.<\/p>",
        "content_alignment": "center",
        "color_scheme": "scheme_1",
        "padding_top": 50,
        "padding_bottom": 50
      }
    },
    "footer-1-5-16": {
      "type": "smi-footer-1-5",
      "blocks": {
        "smi-block-item-0": {
          "type": "image",
          "settings": {
            "heading": "",
            "heading_size": "smi-h5",
            "image_width": 130,
            "use_media_setting": false,
            "img_link": "",
            "content": "",
            "enable_collapsible_content_on_mobile": false
          }
        },
        "smi-block-item-1": {
          "type": "menu",
          "settings": {
            "heading": "Shop",
            "menu": "",
            "enable_collapsible_content_on_mobile": true
          }
        },
        "smi-block-item-2": {
          "type": "menu",
          "settings": {
            "heading": "About",
            "menu": "",
            "enable_collapsible_content_on_mobile": true
          }
        },
        "smi-block-item-3": {
          "type": "menu",
          "settings": {
            "heading": "Support",
            "menu": "",
            "enable_collapsible_content_on_mobile": true
          }
        },
        "smi-block-item-4": {
          "type": "email_form_footer",
          "settings": {
            "heading": "Newsletters",
            "heading_size": "smi-h5",
            "content": "<p>Subscribe to update, access to exclusive deals, and more.<\/p>",
            "style_email_signup": "5",
            "email_notice_text": "No spam, unsubscribe anytime!",
            "enable_collapsible_content_on_mobile": false
          }
        }
      },
      "block_order": [
        "smi-block-item-0",
        "smi-block-item-1",
        "smi-block-item-2",
        "smi-block-item-3",
        "smi-block-item-4"
      ],
      "disabled": true,
      "settings": {
        "full_width": true,
        "icon_style": "none",
        "enable_follow_shop": true,
        "enable_language": false,
        "enable_country": true,
        "show_payment_icon": false,
        "show_policy": true,
        "copyright_text": "",
        "color_scheme": "scheme_2",
        "padding_top": 50,
        "padding_bottom": 50
      }
    },
    "countdown-5-5-18": {
      "type": "smi-countdown-5-5",
      "blocks": {
        "smi-block-item-0": {
          "type": "heading",
          "settings": {
            "sub_heading": "",
            "heading": "Buy today & save 25%",
            "heading_size": "smi-h2",
            "description": ""
          }
        },
        "smi-block-item-1": {
          "type": "countdown_timer",
          "settings": {
            "end_date_time": "2024-06-15",
            "number_size": "smi-h2",
            "countdown_style": "classic_1",
            "hide_expires": true
          }
        },
        "smi-block-item-2": {
          "type": "button",
          "settings": {
            "button_label": "Shop now",
            "button_link": "",
            "button_style": "solid"
          }
        }
      },
      "block_order": [
        "smi-block-item-0",
        "smi-block-item-1",
        "smi-block-item-2"
      ],
      "disabled": true,
      "settings": {
        "full_width": false,
        "content_alignment": "center",
        "color_scheme": "scheme_1",
        "padding_top": 50,
        "padding_bottom": 50
      }
    },
    "rich-text-1-7-19": {
      "type": "smi-rich-text-1-7",
      "blocks": {
        "smi-block-item-0": {
          "type": "image",
          "settings": {
            "heading": "",
            "image_width": 670,
            "use_media_settings": false
          }
        },
        "smi-block-item-1": {
          "type": "heading",
          "settings": {
            "sub_heading": "",
            "heading": "Timeless elegance redefined",
            "heading_size": "smi-h2",
            "description": "<p>Indulge in the allure of runway-inspired fashion. Our collection combines bold styles with timeless grace, offering a curated selection that effortlessly elevates your look.<\/p>"
          }
        },
        "smi-block-item-2": {
          "type": "button",
          "settings": {
            "first_button_label": "Learn more",
            "first_button_link": "",
            "first_button_style": "outline_arrow",
            "second_button_label": "",
            "second_button_link": "",
            "second_button_style": "text",
            "button_full_width": false
          }
        }
      },
      "block_order": [
        "smi-block-item-0",
        "smi-block-item-1",
        "smi-block-item-2"
      ],
      "disabled": true,
      "settings": {
        "full_width": true,
        "content_position": "center",
        "content_alignment": "center",
        "content_max_width": 700,
        "color_scheme": "scheme_2",
        "padding_top": 50,
        "padding_bottom": 50
      }
    },
    "smi_styles_19031": {
      "type": "smi-styles",
      "blocks": {
        "color-0": {
          "type": "color",
          "settings": {
            "background_color1": "#ffffff",
            "background_gradient_color1": "",
            "text_color1": "#121212",
            "subtext_color1": "#000000",
            "solid_background_button_color1": "#121212",
            "solid_button_label_color1": "#ffffff",
            "outline_button_color1": "#121212",
            "shadow_color1": "#121212",
            "background_color2": "#f3f3f3",
            "background_gradient_color2": "",
            "text_color2": "#121212",
            "subtext_color2": "#000000",
            "solid_background_button_color2": "#121212",
            "solid_button_label_color2": "#fcf8f5",
            "outline_button_color2": "#000000",
            "shadow_color2": "#000000",
            "background_color3": "#282828",
            "background_gradient_color3": "",
            "text_color3": "#ffffff",
            "subtext_color3": "#ffffff",
            "solid_background_button_color3": "#ffffff",
            "solid_button_label_color3": "#000000",
            "outline_button_color3": "#ffffff",
            "shadow_color3": "#121212",
            "background_color4": "#121212",
            "background_gradient_color4": "",
            "text_color4": "#ffffff",
            "subtext_color4": "#ffffff",
            "solid_background_button_color4": "#ffffff",
            "solid_button_label_color4": "#121212",
            "outline_button_color4": "#ffffff",
            "shadow_color4": "#121212",
            "background_color5": "#334fb4",
            "background_gradient_color5": "",
            "text_color5": "#ffffff",
            "subtext_color5": "#ffffff",
            "solid_background_button_color5": "#ffffff",
            "solid_button_label_color5": "#334fb4",
            "outline_button_color5": "#ffffff",
            "shadow_color5": "#121212",
            "background_color6": "#ffffff",
            "background_gradient_color6": "",
            "text_color6": "#121212",
            "subtext_color6": "#000000",
            "solid_background_button_color6": "#121212",
            "solid_button_label_color6": "#ffffff",
            "outline_button_color6": "#121212",
            "shadow_color6": "#121212",
            "background_color7": "#ffffff",
            "background_gradient_color7": "",
            "text_color7": "#121212",
            "subtext_color7": "#000000",
            "solid_background_button_color7": "#121212",
            "solid_button_label_color7": "#ffffff",
            "outline_button_color7": "#121212",
            "shadow_color7": "#121212",
            "background_color8": "#ffffff",
            "background_gradient_color8": "",
            "text_color8": "#121212",
            "subtext_color8": "#000000",
            "solid_background_button_color8": "#121212",
            "solid_button_label_color8": "#ffffff",
            "outline_button_color8": "#121212",
            "shadow_color8": "#121212",
            "background_color9": "#ffffff",
            "background_gradient_color9": "",
            "text_color9": "#121212",
            "subtext_color9": "#000000",
            "solid_background_button_color9": "#121212",
            "solid_button_label_color9": "#ffffff",
            "outline_button_color9": "#121212",
            "shadow_color9": "#121212",
            "background_color10": "#ffffff",
            "background_gradient_color10": "",
            "text_color10": "#121212",
            "subtext_color10": "#000000",
            "solid_background_button_color10": "#121212",
            "solid_button_label_color10": "#ffffff",
            "outline_button_color10": "#121212",
            "shadow_color10": "#121212"
          }
        },
        "typography-1": {
          "type": "typography",
          "settings": {
            "overwrite_font": true,
            "type_header_font": "assistant_n4",
            "heading_scale": 100,
            "heading_line_height_scale": 100,
            "heading_letter_spacing_scale": 0.6,
            "heading_text_case": "original",
            "type_body_font": "assistant_n4",
            "body_scale": 100,
            "body_line_height_scale": 100,
            "body_letter_spacing_scale": 0.6,
            "button_font": "body",
            "button_text_case": "original",
            "price_font": "body",
            "menu_font": "body",
            "subheading_font": "body"
          }
        },
        "typography_advance-2": {
          "type": "typography_advance",
          "settings": {
            "fontsize_h1": 40,
            "fontsize_h2": 24,
            "fontsize_h3": 18,
            "fontsize_h4": 15,
            "fontsize_h5": 13,
            "fontsize_h6": 12,
            "fontsize_xs_h1": 40,
            "fontsize_xs_h2": 30,
            "fontsize_xs_h3": 22,
            "fontsize_xs_h4": 20,
            "fontsize_xs_h5": 16,
            "fontsize_xs_h6": 14,
            "fontsize_button": 15,
            "button_letter_spacing_scale": 1,
            "fontweight_button": "400",
            "fontsize_subheading": 14,
            "subheading_letter_spacing_scale": 1,
            "fontweight_subheading": "400",
            "fontsize_badge": 12,
            "badge_letter_spacing_scale": 1,
            "fontweight_badge": "400",
            "fontsize_menu": 14,
            "menu_letter_spacing_scale": 0.6,
            "fontweight_menu": "400",
            "fontsize_price_xl": 18,
            "fontsize_price_lg": 17,
            "fontsize_price_md": 16,
            "price_letter_spacing_scale": 0,
            "fontweight_price": "400"
          }
        },
        "layout-3": {
          "type": "layout",
          "settings": {
            "page_width": 1200,
            "spacing_sections": 0,
            "spacing_elements": 100,
            "spacing_grid_horizontal": 8,
            "spacing_grid_vertical": 8
          }
        },
        "buttons-4": {
          "type": "buttons",
          "settings": {
            "buttons_scale": 100,
            "buttons_border_thickness": 1,
            "buttons_border_opacity": 100,
            "buttons_radius": 0,
            "buttons_shadow": "0,0,0",
            "buttons_shadow_opacity": 15
          }
        },
        "variants-5": {
          "type": "variants",
          "settings": {
            "variant_pills_border_thickness": 1,
            "variant_pills_radius": 40,
            "variant_pills_shadow": "0,0,0",
            "variant_pills_shadow_opacity": 15
          }
        },
        "inputs-6": {
          "type": "inputs",
          "settings": {
            "inputs_border_thickness": 1,
            "inputs_border_opacity": 55,
            "inputs_radius": 0,
            "inputs_shadow": "0,0,0",
            "inputs_shadow_opacity": 15
          }
        },
        "icons-7": {
          "type": "icons",
          "settings": {
            "icon_thickness": 1.2,
            "icon_scale": 100
          }
        },
        "product_cards-8": {
          "type": "product_cards",
          "settings": {
            "card_image_padding": 0,
            "card_border_thickness": 0,
            "card_border_opacity": 10,
            "card_corner_radius": 0,
            "card_shadow": "0,0,0",
            "card_shadow_opacity": 15
          }
        },
        "product_badges-9": {
          "type": "product_badges",
          "settings": {
            "badge_corner_radius": 40,
            "sale_badge_background_color": "#d01717",
            "sale_badge_text_color": "#ffffff",
            "sold_out_badge_background_color": "#8c8c8c",
            "sold_out_badge_text_color": "#ffffff"
          }
        },
        "blog_cards-10": {
          "type": "blog_cards",
          "settings": {
            "blog_card_image_padding": 0,
            "blog_card_border_thickness": 0,
            "blog_card_border_opacity": 10,
            "blog_card_corner_radius": 0,
            "blog_card_shadow": "0,0,0",
            "blog_card_shadow_opacity": 15
          }
        },
        "content_containers-11": {
          "type": "content_containers",
          "settings": {
            "text_boxes_border_thickness": 0,
            "text_boxes_border_opacity": 10,
            "text_boxes_radius": 0,
            "text_boxes_shadow": "0,0,0",
            "text_boxes_shadow_opacity": 15
          }
        },
        "media-12": {
          "type": "media",
          "settings": {
            "media_border_thickness": 1,
            "media_border_opacity": 5,
            "media_radius": 0,
            "media_shadow": "0,0,0",
            "media_shadow_opacity": 15
          }
        },
        "dropdown_popup_drawer-13": {
          "type": "dropdown_popup_drawer",
          "settings": {
            "popup_border_thickness": 1,
            "popup_border_opacity": 10,
            "popup_corner_radius": 0,
            "popup_shadow": "2,4,12",
            "popup_shadow_opacity": 5
          }
        }
      },
      "block_order": [
        "color-0",
        "typography-1",
        "typography_advance-2",
        "layout-3",
        "buttons-4",
        "variants-5",
        "inputs-6",
        "icons-7",
        "product_cards-8",
        "product_badges-9",
        "blog_cards-10",
        "content_containers-11",
        "media-12",
        "dropdown_popup_drawer-13"
      ],
      "settings": {
      }
    }
  },
  "order": [
    "icon-with-text-1-8-0",
    "image-hero-1-2-1",
    "featured-collection-4-2-17",
    "collection-list-1-7-2",
    "comparison-table-1-2-3",
    "testimonial-1-7-4",
    "blog-posts-1-7-5",
    "cart-drawer-1-1-6",
    "collapsible-content-1-1-7",
    "image-with-text-4-7-8",
    "logo-list-4-1-9",
    "rich-content-1-5-10",
    "slideshow-2-3-11",
    "shop-the-look-1-2-12",
    "scrolling-text-1-3-13",
    "featured-product-1-1-14",
    "email-signup-2-5-15",
    "footer-1-5-16",
    "countdown-5-5-18",
    "rich-text-1-7-19",
    "smi_styles_19031"
  ]
}
